{
  "id": "1791768",
  "name": "氧气票务",
  "font_family": "iconfont",
  "css_prefix_text": "icon",
  "description": "文艺演出票务销售网站",
  "glyphs": [
    {
      "icon_id": "1266040",
      "name": "吉他乐器",
      "font_class": "icon-02",
      "unicode": "e60b",
      "unicode_decimal": 58891
    },
    {
      "icon_id": "3079845",
      "name": "京剧",
      "font_class": "jingju",
      "unicode": "e620",
      "unicode_decimal": 58912
    },
    {
      "icon_id": "4147917",
      "name": "乐器",
      "font_class": "leqi",
      "unicode": "e60f",
      "unicode_decimal": 58895
    },
    {
      "icon_id": "11335122",
      "name": "乐器",
      "font_class": "leqi1",
      "unicode": "e60c",
      "unicode_decimal": 58892
    },
    {
      "icon_id": "11487977",
      "name": "arrow-right",
      "font_class": "arrow-right",
      "unicode": "e743",
      "unicode_decimal": 59203
    },
    {
      "icon_id": "248887",
      "name": "登录",
      "font_class": "denglu",
      "unicode": "e608",
      "unicode_decimal": 58888
    },
    {
      "icon_id": "9713056",
      "name": "搜索",
      "font_class": "sousuo",
      "unicode": "e67b",
      "unicode_decimal": 59003
    },
    {
      "icon_id": "1502",
      "name": "说",
      "font_class": "shuo",
      "unicode": "e600",
      "unicode_decimal": 58880
    },
    {
      "icon_id": "1421420",
      "name": "演出服务",
      "font_class": "yanchufuwu",
      "unicode": "e645",
      "unicode_decimal": 58949
    },
    {
      "icon_id": "14321942",
      "name": "消息",
      "font_class": "shouyetubiao-10",
      "unicode": "e622",
      "unicode_decimal": 58914
    }
  ]
}
